<?xml version="1.0" encoding="UTF-8"?>
<export version="E">
  <design>
    <source>D:\Creative projects\Electronics\Traffic Light\Traffic Light\Traffic Light.kicad_sch</source>
    <date>30/11/2022 20:10:01</date>
    <tool>Eeschema (6.0.9)</tool>
    <sheet number="1" name="/" tstamps="/">
      <title_block>
        <title/>
        <company/>
        <rev/>
        <date/>
        <source>Traffic Light.kicad_sch</source>
        <comment number="1" value=""/>
        <comment number="2" value=""/>
        <comment number="3" value=""/>
        <comment number="4" value=""/>
        <comment number="5" value=""/>
        <comment number="6" value=""/>
        <comment number="7" value=""/>
        <comment number="8" value=""/>
        <comment number="9" value=""/>
      </title_block>
    </sheet>
  </design>
  <components>
    <comp ref="D1">
      <value>LED</value>
      <libsource lib="Device" part="LED" description="Light emitting diode"/>
      <property name="Sheetname" value=""/>
      <property name="Sheetfile" value="Traffic Light.kicad_sch"/>
      <sheetpath names="/" tstamps="/"/>
      <tstamps>92791f5e-4730-418f-bff4-cd37041b1574</tstamps>
    </comp>
    <comp ref="D2">
      <value>LED</value>
      <libsource lib="Device" part="LED" description="Light emitting diode"/>
      <property name="Sheetname" value=""/>
      <property name="Sheetfile" value="Traffic Light.kicad_sch"/>
      <sheetpath names="/" tstamps="/"/>
      <tstamps>ab75d279-a748-4e5a-bb20-d2c881d7b557</tstamps>
    </comp>
    <comp ref="D3">
      <value>LED</value>
      <libsource lib="Device" part="LED" description="Light emitting diode"/>
      <property name="Sheetname" value=""/>
      <property name="Sheetfile" value="Traffic Light.kicad_sch"/>
      <sheetpath names="/" tstamps="/"/>
      <tstamps>f51f9e4d-bb89-4d47-ae27-7f0c91e6bea0</tstamps>
    </comp>
    <comp ref="H1">
      <value>MountingHole</value>
      <libsource lib="Mechanical" part="MountingHole" description="Mounting Hole without connection"/>
      <property name="Sheetname" value=""/>
      <property name="Sheetfile" value="Traffic Light.kicad_sch"/>
      <sheetpath names="/" tstamps="/"/>
      <tstamps>2952b400-2300-440b-8ae2-76e09aaffc5c</tstamps>
    </comp>
    <comp ref="H2">
      <value>MountingHole</value>
      <libsource lib="Mechanical" part="MountingHole" description="Mounting Hole without connection"/>
      <property name="Sheetname" value=""/>
      <property name="Sheetfile" value="Traffic Light.kicad_sch"/>
      <sheetpath names="/" tstamps="/"/>
      <tstamps>47de0a9f-51b5-445f-8b71-41b34c3dd803</tstamps>
    </comp>
    <comp ref="H3">
      <value>MountingHole</value>
      <libsource lib="Mechanical" part="MountingHole" description="Mounting Hole without connection"/>
      <property name="Sheetname" value=""/>
      <property name="Sheetfile" value="Traffic Light.kicad_sch"/>
      <sheetpath names="/" tstamps="/"/>
      <tstamps>1866957b-4d4c-4139-b169-a58687de243d</tstamps>
    </comp>
    <comp ref="H4">
      <value>MountingHole</value>
      <libsource lib="Mechanical" part="MountingHole" description="Mounting Hole without connection"/>
      <property name="Sheetname" value=""/>
      <property name="Sheetfile" value="Traffic Light.kicad_sch"/>
      <sheetpath names="/" tstamps="/"/>
      <tstamps>9f3ca170-f72c-452f-a436-3c6cdbb6463d</tstamps>
    </comp>
    <comp ref="J1">
      <value>Conn_01x04</value>
      <libsource lib="Connector_Generic" part="Conn_01x04" description="Generic connector, single row, 01x04, script generated (kicad-library-utils/schlib/autogen/connector/)"/>
      <property name="Sheetname" value=""/>
      <property name="Sheetfile" value="Traffic Light.kicad_sch"/>
      <sheetpath names="/" tstamps="/"/>
      <tstamps>06b0f584-6add-4e98-bfa9-3ce14fe4d662</tstamps>
    </comp>
    <comp ref="R1">
      <value>R</value>
      <libsource lib="Device" part="R" description="Resistor"/>
      <property name="Sheetname" value=""/>
      <property name="Sheetfile" value="Traffic Light.kicad_sch"/>
      <sheetpath names="/" tstamps="/"/>
      <tstamps>d0521102-1868-4b7c-9c7e-d14867daf244</tstamps>
    </comp>
    <comp ref="R2">
      <value>R</value>
      <libsource lib="Device" part="R" description="Resistor"/>
      <property name="Sheetname" value=""/>
      <property name="Sheetfile" value="Traffic Light.kicad_sch"/>
      <sheetpath names="/" tstamps="/"/>
      <tstamps>ec176644-2d51-470a-bfc3-8ea3d6531dbb</tstamps>
    </comp>
    <comp ref="R3">
      <value>R</value>
      <libsource lib="Device" part="R" description="Resistor"/>
      <property name="Sheetname" value=""/>
      <property name="Sheetfile" value="Traffic Light.kicad_sch"/>
      <sheetpath names="/" tstamps="/"/>
      <tstamps>abfabd04-0f28-4240-8cb5-c417d63c4b6b</tstamps>
    </comp>
  </components>
  <libparts>
    <libpart lib="Connector_Generic" part="Conn_01x04">
      <description>Generic connector, single row, 01x04, script generated (kicad-library-utils/schlib/autogen/connector/)</description>
      <docs>~</docs>
      <footprints>
        <fp>Connector*:*_1x??_*</fp>
      </footprints>
      <fields>
        <field name="Reference">J</field>
        <field name="Value">Conn_01x04</field>
        <field name="Datasheet">~</field>
      </fields>
      <pins>
        <pin num="1" name="Pin_1" type="passive"/>
        <pin num="2" name="Pin_2" type="passive"/>
        <pin num="3" name="Pin_3" type="passive"/>
        <pin num="4" name="Pin_4" type="passive"/>
      </pins>
    </libpart>
    <libpart lib="Device" part="LED">
      <description>Light emitting diode</description>
      <docs>~</docs>
      <footprints>
        <fp>LED*</fp>
        <fp>LED_SMD:*</fp>
        <fp>LED_THT:*</fp>
      </footprints>
      <fields>
        <field name="Reference">D</field>
        <field name="Value">LED</field>
        <field name="Datasheet">~</field>
      </fields>
      <pins>
        <pin num="1" name="K" type="passive"/>
        <pin num="2" name="A" type="passive"/>
      </pins>
    </libpart>
    <libpart lib="Device" part="R">
      <description>Resistor</description>
      <docs>~</docs>
      <footprints>
        <fp>R_*</fp>
      </footprints>
      <fields>
        <field name="Reference">R</field>
        <field name="Value">R</field>
        <field name="Datasheet">~</field>
      </fields>
      <pins>
        <pin num="1" name="" type="passive"/>
        <pin num="2" name="" type="passive"/>
      </pins>
    </libpart>
    <libpart lib="Mechanical" part="MountingHole">
      <description>Mounting Hole without connection</description>
      <docs>~</docs>
      <footprints>
        <fp>MountingHole*</fp>
      </footprints>
      <fields>
        <field name="Reference">H</field>
        <field name="Value">MountingHole</field>
        <field name="Datasheet">~</field>
      </fields>
    </libpart>
  </libparts>
  <libraries>
    <library logical="Connector_Generic">
      <uri>E:\Electronics\6.0\share\kicad\symbols\/Connector_Generic.kicad_sym</uri>
    </library>
    <library logical="Device">
      <uri>E:\Electronics\6.0\share\kicad\symbols\/Device.kicad_sym</uri>
    </library>
    <library logical="Mechanical">
      <uri>E:\Electronics\6.0\share\kicad\symbols\/Mechanical.kicad_sym</uri>
    </library>
  </libraries>
  <nets>
    <net code="1" name="Net-(D1-Pad1)">
      <node ref="D1" pin="1" pinfunction="K" pintype="passive"/>
      <node ref="D2" pin="1" pinfunction="K" pintype="passive"/>
      <node ref="D3" pin="1" pinfunction="K" pintype="passive"/>
      <node ref="J1" pin="4" pinfunction="Pin_4" pintype="passive"/>
    </net>
    <net code="2" name="Net-(D1-Pad2)">
      <node ref="D1" pin="2" pinfunction="A" pintype="passive"/>
      <node ref="R1" pin="1" pintype="passive"/>
    </net>
    <net code="3" name="Net-(D2-Pad2)">
      <node ref="D2" pin="2" pinfunction="A" pintype="passive"/>
      <node ref="R2" pin="1" pintype="passive"/>
    </net>
    <net code="4" name="Net-(D3-Pad2)">
      <node ref="D3" pin="2" pinfunction="A" pintype="passive"/>
      <node ref="R3" pin="1" pintype="passive"/>
    </net>
    <net code="5" name="Net-(J1-Pad1)">
      <node ref="J1" pin="1" pinfunction="Pin_1" pintype="passive"/>
      <node ref="R3" pin="2" pintype="passive"/>
    </net>
    <net code="6" name="Net-(J1-Pad2)">
      <node ref="J1" pin="2" pinfunction="Pin_2" pintype="passive"/>
      <node ref="R2" pin="2" pintype="passive"/>
    </net>
    <net code="7" name="Net-(J1-Pad3)">
      <node ref="J1" pin="3" pinfunction="Pin_3" pintype="passive"/>
      <node ref="R1" pin="2" pintype="passive"/>
    </net>
  </nets>
</export>
